[
  {
    "id": 1763396520170,
    "type": "compliance_check",
    "title": "Compliance Score Decreased",
    "message": "Your overall compliance score decreased from 88% to 84%",
    "severity": "warning",
    "timestamp": "2025-11-17T18:22:00.170771",
    "read": false
  },
  {
    "id": 1763396520170,
    "type": "regulatory_change",
    "title": "New Regulatory Update",
    "message": "GDPR Article 32 has been updated. Review recommended.",
    "severity": "info",
    "timestamp": "2025-11-17T18:22:00.170771",
    "read": false
  }
]